lugano/ej30/rtl/full_adder_cell.vhd
library ieee ;
    use ieee.std_logic_1164.all ;
    use ieee.numeric_std.all ;

entity full_adder_cell is
  port 
  (
    a, b, ci   : in std_logic;
    o, co   : out std_logic
  );
end full_adder_cell ; 

architecture arch of full_adder_cell is

begin

    co<= (a and b) or (ci and b) or (ci and a);
    o<= a xor b xor ci;

end architecture ;

lugano/ej30/rtl/full_adder_generic.vhd
library ieee ;
    use ieee.std_logic_1164.all ;
    use ieee.numeric_std.all ;

entity full_adder_generic is
    generic
    (
        N : natural :=16
    );
    port 
    (
        a, b: in std_logic_vector(N-1 downto 0);
        ci : in std_logic;
        o : out std_logic_vector(N-1 downto 0);
        co : out std_logic
    ) ;
end full_adder_generic ; 

architecture arch of full_adder_generic is

    component full_adder_cell
    port(
        a, b, ci   : in std_logic;
        o, co   : out std_logic
    );
    end component;

    signal c: std_logic_vector(N-1 downto 0);

begin
    
    state_gen : for i in 0 to N-1 generate
        first_gen: 
            if(i=0) generate 
                entrada : full_adder_cell
                    port map(
                        a=>a(i),
                        b=>b(i),
                        ci=>ci,
                        o=>o(i),
                        co=>c(i+1)
                    );
            end generate;
        
        middle_gen:
            if ( (i>0) and (i<N-1) ) generate
                gen: full_adder_cell
                    port map(
                        a=>a(i),
                        b=>b(i),
                        ci=>c(i),
                        o=>o(i),
                        co=>c(i+1)
                    );
                end generate;

        last_gen:
            if(i=(N-1)) generate
                salida: full_adder_cell
                port map(
                    a=>a(i),
                    b=>b(i),
                    ci=>c(i),
                    o=>o(i),
                    co=>co
                );
        end generate;
    end generate;
end architecture ;

lugano/ej30/sim/full_adder_generic_tb.vhd
library ieee;
use ieee.std_logic_1164.all;
USE ieee.numeric_std.all;
use work.random_stim_pkg.all;
use work.report_pkg.all;
use work.gldn_mdl_pkg.all;

entity full_adder_generic_tb is
    generic (
        N: natural := 4
    );
end entity full_adder_generic_tb;

architecture simulation of full_adder_generic_tb is

    signal            vif_a       : std_logic_vector(N-1 downto 0)  := (others => '0');
    signal            vif_b       : std_logic_vector(N-1 downto 0)  := (others => '0');
    signal            vif_ci      : std_logic                       := '0';
    signal            vif_o       : std_logic_vector(N-1 downto 0);
    signal            vif_co      : std_logic;

    shared variable   var_a       : std_logic_vector(N-1 downto 0);
    shared variable   var_b       : std_logic_vector(N-1 downto 0);
    shared variable   exp_o       : std_logic_vector(N downto 0);
    shared variable   exp_co      : std_logic;
    shared variable   errors      : integer   := 0;
    shared variable   end_of_sim  : std_logic := '0';
 
begin

    -- instantiate the unit under test (uut)			
    uut: entity work.full_adder_generic
    generic map(
        N     => N
    )
    port map(
        a  => vif_a ,
        b  => vif_b ,
        ci => vif_ci,
        o  => vif_o ,
        co => vif_co
    );

    -- Stimulus process
    stim_proc: process begin
        report_begin;
        for i in 0 to 7 loop
            var_a := random_vector(N);
            for j in 0 to 7 loop
                var_b  := random_vector(N);
                exp_o  := std_logic_vector(('0' & unsigned(var_a)) + ('0' & unsigned(var_b)));
                exp_co := exp_o(N);
                vif_a  <= var_a;
                vif_b  <= var_b;
                wait for 5 ns;
                if report_error(exp_o(N-1 downto 0), vif_o, "o", "dec") then
                    errors := errors + 1;
                end if;
                if report_error_bit(exp_co, vif_co, "co") then
                    errors := errors + 1;
                end if;
                wait for 5 ns;
            end loop;
        end loop;
        report_pass_fail(errors);
        report_end;
        wait;
    end process;

end architecture simulation;

lugano/ej30/waves.vcd
$date
  Tue Nov 29 15:25:02 2022
$end
$version
  GHDL v0
$end
$timescale
  1 fs
$end
$scope module standard $end
$upscope $end
$scope module std_logic_1164 $end
$upscope $end
$scope module numeric_std $end
$upscope $end
$scope module math_real $end
$upscope $end
$scope module random_stim_pkg $end
$upscope $end
$scope module report_pkg $end
$upscope $end
$scope module gldn_mdl_pkg $end
$upscope $end
$scope module full_adder_generic_tb $end
$var reg 4 ! vif_a[3:0] $end
$var reg 4 " vif_b[3:0] $end
$var reg 1 # vif_ci $end
$var reg 4 $ vif_o[3:0] $end
$var reg 1 % vif_co $end
$scope module uut $end
$var reg 4 & a[3:0] $end
$var reg 4 ' b[3:0] $end
$var reg 1 ( ci $end
$var reg 4 ) o[3:0] $end
$var reg 1 * co $end
$var reg 4 + c[3:0] $end
$scope module state_gen(0) $end
$scope module first_gen $end
$scope module entrada $end
$var reg 1 , a $end
$var reg 1 - b $end
$var reg 1 . ci $end
$var reg 1 / o $end
$var reg 1 0 co $end
$upscope $end
$upscope $end
$upscope $end
$scope module state_gen(1) $end
$scope module middle_gen $end
$scope module gen $end
$var reg 1 1 a $end
$var reg 1 2 b $end
$var reg 1 3 ci $end
$var reg 1 4 o $end
$var reg 1 5 co $end
$upscope $end
$upscope $end
$upscope $end
$scope module state_gen(2) $end
$scope module middle_gen $end
$scope module gen $end
$var reg 1 6 a $end
$var reg 1 7 b $end
$var reg 1 8 ci $end
$var reg 1 9 o $end
$var reg 1 : co $end
$upscope $end
$upscope $end
$upscope $end
$scope module state_gen(3) $end
$scope module last_gen $end
$scope module salida $end
$var reg 1 ; a $end
$var reg 1 < b $end
$var reg 1 = ci $end
$var reg 1 > o $end
$var reg 1 ? co $end
$upscope $end
$upscope $end
$upscope $end
$upscope $end
$upscope $end
$enddefinitions $end
#0
b0000 !
b0000 "
0#
b0000 $
0%
b0000 &
b0000 '
0(
b0000 )
0*
b000U +
0,
0-
0.
0/
00
01
02
03
04
05
06
07
08
09
0:
0;
0<
0=
0>
0?
#5000000
#10000000
b0011 "
b0011 $
b0011 '
b0011 )
1-
1/
12
14
#15000000
#20000000
b1100 "
b1100 $
b1100 '
b1100 )
0-
0/
02
04
17
19
1<
1>
#25000000
#30000000
b1101 "
b1101 $
b1101 '
b1101 )
1-
1/
#35000000
#40000000
b1111 "
b1111 $
b1111 '
b1111 )
12
14
#45000000
#50000000
b0110 "
b0110 $
b0110 '
b0110 )
0-
0/
0<
0>
#55000000
#60000000
b0011 "
b0011 $
b0011 '
b0011 )
1-
1/
07
09
#65000000
#70000000
b1001 "
b1001 $
b1001 '
b1001 )
02
04
1<
1>
#75000000
#80000000
b0001 !
b0011 "
b0100 $
b0001 &
b0011 '
b0100 )
b011U +
1,
0/
10
12
13
04
15
18
19
0<
0>
#85000000
#90000000
b1010 "
b1011 $
b1010 '
b1011 )
b000U +
0-
1/
00
03
14
05
08
09
1<
1>
#95000000
#100000000
b1101 "
b1110 $
b1101 '
b1110 )
b001U +
1-
0/
10
02
13
14
17
19
#105000000
#110000000
b1000 "
b1001 $
b1000 '
b1001 )
b000U +
0-
1/
00
03
04
07
09
#115000000
#120000000
#125000000
#130000000
b0111 "
b1000 $
b0111 '
b1000 )
b111U +
1-
0/
10
12
13
04
15
17
18
09
1:
0<
1=
1>
#135000000
#140000000
#145000000
#150000000
b1101 "
b1110 $
0%
b1101 '
b1110 )
0*
b001U +
02
14
05
08
19
0:
1<
0=
1>
0?
#155000000
#160000000
b0011 !
b0101 "
b1000 $
b0011 &
b0101 '
b1000 )
b111U +
11
04
15
18
09
1:
0<
1=
1>
#165000000
#170000000
b1010 "
b1101 $
0%
b1010 '
b1101 )
0*
b010U +
0-
1/
00
12
03
04
07
19
0:
1<
0=
1>
0?
#175000000
#180000000
#185000000
#190000000
b1011 "
b1110 $
b1011 '
b1110 )
b011U +
1-
0/
10
13
14
#195000000
#200000000
b1100 "
b1111 $
0%
b1100 '
b1111 )
0*
b000U +
0-
1/
00
02
03
14
05
17
08
19
0:
0=
1>
0?
#205000000
#210000000
b0010 "
b0101 $
b0010 '
b0101 )
b010U +
12
04
15
07
18
19
0<
0>
#215000000
#220000000
b0101 "
b1000 $
b0101 '
b1000 )
b111U +
1-
0/
10
02
13
04
15
17
18
09
1:
1=
1>
#225000000
#230000000
b1101 "
b0000 $
1%
b1101 '
b0000 )
1*
1<
0>
1?
#235000000
#240000000
b1100 !
b1000 "
b0100 $
b1100 &
b1000 '
b0100 )
b000U +
0,
0-
00
01
03
04
05
16
07
08
19
0:
1;
0=
0>
#245000000
#250000000
b1110 "
b1010 $
b1110 '
b1010 )
b100U +
12
14
17
09
1:
1=
1>
#255000000
#260000000
b0001 "
b1101 $
0%
b0001 '
b1101 )
0*
b000U +
1-
1/
02
04
07
19
0:
0<
0=
1>
0?
#265000000
#270000000
b0011 "
b1111 $
b0011 '
b1111 )
12
14
#275000000
#280000000
b1101 "
b1001 $
1%
b1101 '
b1001 )
1*
b100U +
02
04
17
09
1:
1<
1=
1>
1?
#285000000
#290000000
b1110 "
b1010 $
b1110 '
b1010 )
0-
0/
12
14
#295000000
#300000000
b0100 "
b0000 $
b0100 '
b0000 )
02
04
0<
0>
#305000000
#310000000
b1100 "
b1000 $
b1100 '
b1000 )
1<
1>
#315000000
#320000000
b0011 !
b1011 "
b1110 $
0%
b0011 &
b1011 '
b1110 )
0*
b011U +
1,
1-
10
11
12
13
14
15
06
07
18
19
0:
0;
0=
1>
0?
#325000000
#330000000
b0110 "
b1001 $
b0110 '
b1001 )
b110U +
0-
1/
00
03
04
17
09
1:
0<
1=
1>
#335000000
#340000000
b1001 "
b1100 $
0%
b1001 '
b1100 )
0*
b011U +
1-
0/
10
02
13
04
15
07
18
19
0:
1<
0=
1>
0?
#345000000
#350000000
b0110 "
b1001 $
b0110 '
b1001 )
b110U +
0-
1/
00
12
03
04
17
09
1:
0<
1=
1>
#355000000
#360000000
b1100 "
b1111 $
0%
b1100 '
b1111 )
0*
b000U +
02
14
05
08
19
0:
1<
0=
1>
0?
#365000000
#370000000
b0111 "
b1010 $
b0111 '
b1010 )
b111U +
1-
0/
10
12
13
14
15
18
09
1:
0<
1=
1>
#375000000
#380000000
b0001 "
b0100 $
b0001 '
b0100 )
b011U +
02
04
07
19
0:
0=
0>
#385000000
#390000000
b1100 "
b1111 $
0%
b1100 '
b1111 )
0*
b000U +
0-
1/
00
03
14
05
17
08
19
0:
1<
0=
1>
0?
#395000000
#400000000
b1110 !
b0001 "
b1110 &
b0001 '
0,
1-
16
07
1;
0<
#405000000
#410000000
b1010 "
b1000 $
1%
b1010 '
b1000 )
1*
b110U +
0-
0/
12
04
15
18
09
1:
1<
1=
1>
1?
#415000000
#420000000
b1101 "
b1011 $
b1101 '
b1011 )
b100U +
1-
1/
02
14
05
17
08
09
#425000000
#430000000
b0001 "
b1111 $
0%
b0001 '
b1111 )
0*
b000U +
07
19
0:
0<
0=
1>
0?
#435000000
#440000000
b0010 "
b0000 $
1%
b0010 '
b0000 )
1*
b110U +
0-
0/
12
04
15
18
09
1:
1=
0>
1?
#445000000
#450000000
b0011 "
b0001 $
b0011 '
b0001 )
1-
1/
#455000000
#460000000
b1011 "
b1001 $
b1011 '
b1001 )
1<
1>
#465000000
#470000000
b0100 "
b0010 $
b0100 '
b0010 )
b100U +
0-
0/
02
14
05
17
08
09
0<
0>
#475000000
#480000000
b1100 !
b0110 "
b1100 &
b0110 '
01
12
#485000000
#490000000
b0011 "
b1111 $
0%
b0011 '
b1111 )
0*
b000U +
1-
1/
07
19
0:
0=
1>
0?
#495000000
#500000000
b0101 "
b0001 $
1%
b0101 '
b0001 )
1*
b100U +
02
04
17
09
1:
1=
0>
1?
#505000000
#510000000
b0111 "
b0011 $
b0111 '
b0011 )
12
14
#515000000
#520000000
b0101 "
b0001 $
b0101 '
b0001 )
02
04
#525000000
#530000000
b1011 "
b0111 $
b1011 '
b0111 )
b000U +
12
14
07
19
0:
1<
0=
0>
#535000000
#540000000
b1101 "
b1001 $
b1101 '
b1001 )
b100U +
02
04
17
09
1:
1=
1>
#545000000
#550000000
b0101 "
b0001 $
b0101 '
b0001 )
0<
0>
#555000000
#560000000
b1011 !
b0010 "
b1101 $
0%
b1011 &
b0010 '
b1101 )
0*
b010U +
1,
0-
11
12
15
06
07
18
19
0:
0=
1>
0?
#565000000
#570000000
b0100 "
b1111 $
0%
b0100 '
b1111 )
0*
b000U +
02
14
05
17
08
19
0:
0=
1>
0?
#575000000
#580000000
b1010 "
b0101 $
1%
b1010 '
b0101 )
1*
b010U +
12
04
15
07
18
19
1<
0>
1?
#585000000
#590000000
b0011 "
b1110 $
0%
b0011 '
b1110 )
0*
b011U +
1-
0/
10
13
14
0<
1>
0?
#595000000
#600000000
#605000000
#610000000
b1101 "
b1000 $
1%
b1101 '
b1000 )
1*
b111U +
02
04
17
09
1:
1<
1=
1>
1?
#615000000
#620000000
b0111 "
b0010 $
b0111 '
b0010 )
12
14
0<
0>
#625000000
#630000000
b0010 "
b1101 $
0%
b0010 '
b1101 )
0*
b010U +
0-
1/
00
03
04
07
19
0:
0=
1>
0?
